{
  "crashes": null,
  "game": {
    "id": 1637104475,
    "level": 6,
    "maxTick": 900,
    "seed": 841,
    "size": 21
  },
  "results": [
    {
      "lastTick": 1011,
      "player": 1,
      "score": 2875.0,
      "version": "final_v2@600"
    },
    {
      "lastTick": 1012,
      "player": 2,
      "score": 2833.0,
      "version": "final_v3@600"
    },
    {
      "lastTick": 1012,
      "player": 3,
      "score": 2893.0,
      "version": "final_v4@600"
    },
    {
      "lastTick": 1012,
      "player": 4,
      "score": 3015.0,
      "version": "local@600"
    }
  ]
}