{
  "crashes": null,
  "game": {
    "id": 1637103004,
    "level": 7,
    "maxTick": 800,
    "seed": 721,
    "size": 21
  },
  "results": [
    {
      "lastTick": 912,
      "player": 1,
      "score": 1868.0,
      "version": "final_v2@600"
    },
    {
      "lastTick": 336,
      "player": 2,
      "score": 1374.47998046875,
      "version": "final_v3@600"
    },
    {
      "lastTick": 912,
      "player": 3,
      "score": 3038.0,
      "version": "final_v4@600"
    },
    {
      "lastTick": 912,
      "player": 4,
      "score": 3460.0,
      "version": "local@600"
    }
  ]
}