{
  "crashes": null,
  "game": {
    "id": 1637135763,
    "level": 5,
    "maxTick": 850,
    "seed": 773,
    "size": 17
  },
  "results": [
    {
      "lastTick": 923,
      "player": 1,
      "score": 1810.0,
      "version": "final_v2@600"
    },
    {
      "lastTick": 924,
      "player": 2,
      "score": 1756.0,
      "version": "final_v3@600"
    },
    {
      "lastTick": 924,
      "player": 3,
      "score": 1548.0,
      "version": "final_v4@600"
    },
    {
      "lastTick": 924,
      "player": 4,
      "score": 1746.0,
      "version": "local@600"
    }
  ]
}