{
  "crashes": null,
  "game": {
    "id": 1637242435,
    "level": 9,
    "maxTick": 1000,
    "seed": 933,
    "size": 21
  },
  "results": [
    {
      "lastTick": 1112,
      "player": 1,
      "score": 2738.0,
      "version": "final_v5@600"
    },
    {
      "lastTick": 1112,
      "player": 2,
      "score": 2712.0,
      "version": "final_v5@600"
    },
    {
      "lastTick": 1112,
      "player": 3,
      "score": 2780.0,
      "version": "final_v5@600"
    },
    {
      "lastTick": 1112,
      "player": 4,
      "score": 2990.0,
      "version": "local@600"
    }
  ]
}