{
  "crashes": null,
  "game": {
    "id": 1637050971,
    "level": 4,
    "maxTick": 1000,
    "seed": 474,
    "size": 21
  },
  "results": [
    {
      "lastTick": 1112,
      "player": 1,
      "score": 3324.0,
      "version": "final_v3@600"
    },
    {
      "lastTick": 1112,
      "player": 2,
      "score": 3276.0,
      "version": "final_v3@600"
    },
    {
      "lastTick": 1112,
      "player": 3,
      "score": 3264.0,
      "version": "final_v3@600"
    },
    {
      "lastTick": 1112,
      "player": 4,
      "score": 3288.0,
      "version": "local@600"
    }
  ]
}