{
  "crashes": null,
  "game": {
    "id": 1637251674,
    "level": 7,
    "maxTick": 800,
    "seed": 721,
    "size": 21
  },
  "results": [
    {
      "lastTick": 911,
      "player": 1,
      "score": 2275.0,
      "version": "final_v4@600"
    },
    {
      "lastTick": 911,
      "player": 2,
      "score": 2851.0,
      "version": "final_v5@600"
    },
    {
      "lastTick": 911,
      "player": 3,
      "score": 2569.0,
      "version": "final_v6@600"
    },
    {
      "lastTick": 911,
      "player": 4,
      "score": 2557.0,
      "version": "local@600"
    }
  ]
}