{
  "crashes": null,
  "game": {
    "id": 1636951668,
    "level": 10,
    "maxTick": 800,
    "seed": 841,
    "size": 15
  },
  "results": [
    {
      "lastTick": 859,
      "player": 1,
      "score": 2622.0,
      "version": "final_v2@600"
    },
    {
      "lastTick": 859,
      "player": 2,
      "score": 2594.0,
      "version": "final_v1@600"
    },
    {
      "lastTick": 859,
      "player": 3,
      "score": 2738.0,
      "version": "final_v1@600"
    },
    {
      "lastTick": 859,
      "player": 4,
      "score": 2606.0,
      "version": "final_v1@600"
    }
  ]
}