{
  "crashes": null,
  "game": {
    "id": 1637093863,
    "level": 9,
    "maxTick": 1000,
    "seed": 609,
    "size": 21
  },
  "results": [
    {
      "lastTick": 1112,
      "player": 1,
      "score": 2592.0,
      "version": "final_v3@600"
    },
    {
      "lastTick": 1112,
      "player": 2,
      "score": 2568.0,
      "version": "final_v3@600"
    },
    {
      "lastTick": 1112,
      "player": 3,
      "score": 2574.0,
      "version": "final_v3@600"
    },
    {
      "lastTick": 1112,
      "player": 4,
      "score": 2490.0,
      "version": "local@600"
    }
  ]
}